holonet/__init__.py
holonet/core/__init__.py
holonet/core/nodes.py
holonet/core/packets.py
holonet/decoding/__init__.py
holonet/decoding/signal_reader.py
holonet/embedded/__init__.py
holonet/embedded/micropython_adapter.py
holonet/hardware/__init__.py
holonet/hardware/induction_driver.py
holonet/interface/__init__.py
holonet/interface/fastapi_app.py
holonet/interface/websocket_bridge.py
holonet/modulation/__init__.py
holonet/modulation/patterns.py
holonet/mtq/__init__.py
holonet/mtq/coherence_controller.py
holonet/mtq/decorators.py
holonet/mtq/optimizer.py
holonet/mtq/quantum_interface_ibm.py
holonet/mtq/quantum_packet.py
holonet/mtq/state_models.py
holonet/mtq/tunnel_engine.py
holonet/network/__init__.py
holonet/network/adaptive_topology.py
holonet/network/chord_client.py
holonet/network/decorators.py
holonet/network/holo_node.py
holonet/network/metrics.py
holonet/network/overlay.py
holonet/network/quantum_router.py
holonet/network/topology.py
holonet/security/__init__.py
holonet/security/leptonic_crypto.py
holonet/security/leptonic_guard.py
holonet/security/token_store.py
holonet/simulation/__init__.py
holonet/simulation/adaptive_controller.py
holonet/simulation/benchmarking.py
holonet/simulation/engine.py
holonet/simulation/mtq_env.py
holonet/simulation/visualizer.py
holonet/transmission/__init__.py
holonet/transmission/fiber.py
holonet/transmission/mtq_bridge.py
holonet_py-1.0.0.dist-info/METADATA
holonet_py-1.0.0.dist-info/WHEEL
holonet_py-1.0.0.dist-info/top_level.txt
holonet_py-1.0.0.dist-info/RECORD
