Metadata-Version: 2.4
Name: holonet-py
Version: 1.0.0
Summary: Infraestructura experimental para la simulación de redes muónicas holográficas
Author-email: Equipo Holonet <equipo@example.com>
Project-URL: Homepage, https://github.com/holonet-labs/holonet-py
Project-URL: Repository, https://github.com/holonet-labs/holonet-py
Project-URL: Documentation, https://holonet-labs.github.io/holonet-py
Requires-Python: >=3.10
Requires-Dist: numpy
Requires-Dist: scipy
Requires-Dist: fastapi
Requires-Dist: httpx
Requires-Dist: uvicorn[standard]
Requires-Dist: websockets
Requires-Dist: pyzmq
Requires-Dist: rpyc
Requires-Dist: torch
Requires-Dist: pydantic
Requires-Dist: PyYAML
Provides-Extra: docs
Requires-Dist: mkdocs; extra == "docs"
Requires-Dist: mkdocs-material; extra == "docs"
Requires-Dist: matplotlib; extra == "docs"
Requires-Dist: mkdocs-htmlproofer-plugin; extra == "docs"
Provides-Extra: tests
Requires-Dist: pytest; extra == "tests"
Requires-Dist: httpx; extra == "tests"
